README.rst
setup.cfg
setup.py
PyMCP2221A/PyMCP2221A.py
PyMCP2221A/SMBus.py
PyMCP2221A/__init__.py
PyMCP2221A.egg-info/PKG-INFO
PyMCP2221A.egg-info/SOURCES.txt
PyMCP2221A.egg-info/dependency_links.txt
PyMCP2221A.egg-info/requires.txt
PyMCP2221A.egg-info/top_level.txt