Metadata-Version: 1.0
Name: PyMCP2221A
Version: 1.3.0
Summary: This is a Microchip MCP2221(A) HID Library by python3.
Home-page: https://github.com/nonNoise/PyMCP2221A
Author:  Yuta Kitagami
Author-email: kitagami@artifactnoise.com
License: MIT License
Keywords: Hardware,USB,HID,MCP2221,I2C,GPIO,I2C,SMBus
Platform: Linux
Platform: Windows
Platform: Mac
